playvision
