Metadata-Version: 2.1
Name: playvision-devops-tools
Version: 0.0.10
Summary: Playvision devops tools
Home-page: UNKNOWN
Author: Dmitriy Shelestovskiy
Author-email: one@sonhador.ru
License: UNKNOWN
Platform: UNKNOWN
Classifier: Programming Language :: Python :: 3
Requires-Python: >=3.6
